LICENSE
README.md
setup.py
sengbao/__init__.py
sengbao.egg-info/PKG-INFO
sengbao.egg-info/SOURCES.txt
sengbao.egg-info/dependency_links.txt
sengbao.egg-info/not-zip-safe
sengbao.egg-info/requires.txt
sengbao.egg-info/top_level.txt
sengbao/cores/__init__.py
sengbao/cores/minuit.py
sengbao/cores/util.py
sengbao/distributions/__init__.py
sengbao/model/__init__.py
sengbao/model/model.py
sengbao/tests/__init__.py
sengbao/variable/__init__.py
sengbao/variable/variable.py
tests/__init__.py