Metadata-Version: 2.1
Name: sengbao
Version: 0.4
Summary: High Performance Maximum Likelihood Estimations
Home-page: http://github.com/ibab/python-mle
Author: sengbao
License: MIT
Platform: UNKNOWN
License-File: LICENSE
